{"type":"FeatureCollection","features":[{"type":"Feature","geometry":{"type":"Point","coordinates":[-98.4936,29.6135]},"properties":{"name":"North Central Baptist Hospital","marker-color":"#8a2be2"},"id":0},{"type":"Feature","geometry":{"type":"Point","coordinates":[-98.5475,29.4897]},"properties":{"name":"Texsan","marker-color":"#8a2be2"},"id":1},{"type":"Feature","geometry":{"type":"Point","coordinates":[-98.4623,29.6165]},"properties":{"name":"ROC","marker-color":"#8a2be2"},"id":2}]}